grid_reducer/__init__.py
grid_reducer/add_differential_privacy.py
grid_reducer/aggregate_primary.py
grid_reducer/aggregate_secondary.py
grid_reducer/create_registry.py
grid_reducer/network.py
grid_reducer/opendss.py
grid_reducer/plot.py
grid_reducer/reducer.py
grid_reducer/rename_components.py
grid_reducer/smartds.py
grid_reducer/summary.py
grid_reducer/transform_coordinate.py
grid_reducer/version.py
grid_reducer/aggregators/__init__.py
grid_reducer/aggregators/generators.py
grid_reducer/aggregators/line.py
grid_reducer/aggregators/loads.py
grid_reducer/aggregators/pvsystems.py
grid_reducer/aggregators/registry.py
grid_reducer/aggregators/storages.py
grid_reducer/altdss/__init__.py
grid_reducer/altdss/altdss_models.py
grid_reducer/altdss/pydantic_complex.py
grid_reducer/cli/__init__.py
grid_reducer/cli/cli.py
grid_reducer/cli/reducer.py
grid_reducer/similarity/__init__.py
grid_reducer/similarity/line.py
grid_reducer/similarity/similarity.py
grid_reducer/utils/__init__.py
grid_reducer/utils/ckt.py
grid_reducer/utils/data.py
grid_reducer/utils/display.py
grid_reducer/utils/files.py
grid_reducer/utils/parser.py
grid_reducer-1.1.1.dist-info/METADATA
grid_reducer-1.1.1.dist-info/WHEEL
grid_reducer-1.1.1.dist-info/entry_points.txt
grid_reducer-1.1.1.dist-info/licenses/LICENSE
grid_reducer-1.1.1.dist-info/RECORD
