Metadata-Version: 2.4
Name: grid_reducer
Version: 1.1.1
Summary: A repository for performing network reduction on distribution network model.
Project-URL: Documentation, https://grid-atlas.github.io/grid-reducer/latest/
Project-URL: Issues, https://github.com/grid-atlas/grid-reducer/issues
Project-URL: Source, https://github.com/grid-atlas/grid-reducer
Author-email: Kapil Duwadi <kapil.duwadi@pnnl.gov>, Kaustav Bhattacharjee <kaustav.bhattacharjee@pnnl.gov>, Alexander Anderson <Alexander.Anderson@pnnl.gov>, Rabayet Sadnan <rabayet.sadnan@pnnl.gov>
License-Expression: BSD-3-Clause
License-File: LICENSE
Classifier: Programming Language :: Python :: 3.11
Classifier: Programming Language :: Python :: 3.12
Classifier: Programming Language :: Python :: 3.13
Requires-Python: >=3.11
Requires-Dist: click~=8.2.1
Requires-Dist: fsspec~=2025.5.1
Requires-Dist: geopandas~=1.1.0
Requires-Dist: mapclassify~=2.9.0
Requires-Dist: matplotlib~=3.10.3
Requires-Dist: networkx~=3.5
Requires-Dist: opendssdirect-py~=0.9.4
Requires-Dist: pint~=0.24.4
Requires-Dist: pydantic~=2.11.5
Requires-Dist: rich~=14.0.0
Requires-Dist: s3fs~=2025.5.1
Requires-Dist: scikit-learn~=1.7.2
Requires-Dist: scipy~=1.15.3
Requires-Dist: tqdm~=4.67.1
Provides-Extra: dev
Requires-Dist: pre-commit~=4.2.0; extra == 'dev'
Requires-Dist: pytest-cov~=7.0.0; extra == 'dev'
Requires-Dist: pytest-mock~=3.14.1; extra == 'dev'
Requires-Dist: pytest~=8.4.0; extra == 'dev'
Requires-Dist: ruff~=0.11.12; extra == 'dev'
Provides-Extra: doc
Requires-Dist: mike~=2.1.3; extra == 'doc'
Requires-Dist: mkdocs-material~=9.6.14; extra == 'doc'
